mycroft_tts_plugin_azure/__init__.py
mycroft_tts_plugin_azure-0.1.dist-info/LICENSE.txt
mycroft_tts_plugin_azure-0.1.dist-info/METADATA
mycroft_tts_plugin_azure-0.1.dist-info/WHEEL
mycroft_tts_plugin_azure-0.1.dist-info/entry_points.txt
mycroft_tts_plugin_azure-0.1.dist-info/top_level.txt
mycroft_tts_plugin_azure-0.1.dist-info/zip-safe
mycroft_tts_plugin_azure-0.1.dist-info/RECORD
