Metadata-Version: 2.1
Name: mycroft-tts-plugin-azure
Version: 0.1
Summary: A tts plugin for mycroft, using Azure Cognitive Services
Home-page: http://github.com/dalgwen/mycroft-tts-plugin-azure
Author: Gwendal Roulleau
Author-email: private@private.org
License: Apache-2.0
Keywords: mycroft plugin tts
Platform: UNKNOWN
Classifier: Development Status :: 3 - Alpha
Classifier: Intended Audience :: Developers
Classifier: Topic :: Text Processing :: Linguistic
Classifier: License :: OSI Approved :: Apache Software License
Classifier: Programming Language :: Python :: 3.7
